data/[Model 2.224x][Find safe and unsafe images 2.224][safe maybe unsafe][2].h5
"data/[Model 3.224x][Find safe, maybe and unsafe images 3.224][safe unsafe][1].h5"
data/index.html
imageanalyzer/__init__.py
imageanalyzer/__main__.py
imageanalyzer/imageanalyzer.py
image_analyzer-0.1.dist-info/METADATA
image_analyzer-0.1.dist-info/WHEEL
image_analyzer-0.1.dist-info/entry_points.txt
image_analyzer-0.1.dist-info/top_level.txt
image_analyzer-0.1.dist-info/RECORD
