Metadata-Version: 2.1
Name: image-analyzer
Version: 0.1
Summary: Browsers options
Home-page: https://github.com/qeeqbox/image-analyzer
Author: QeeqBox
Author-email: gigaqeeq@gmail.com
License: AGPL-3.0
Platform: UNKNOWN
Requires-Python: >=3.5
Requires-Dist: Pillow
Requires-Dist: aiohttp
Requires-Dist: asyncio
Requires-Dist: bs4
Requires-Dist: galeodes
Requires-Dist: keras
Requires-Dist: numpy
Requires-Dist: opencv-python
Requires-Dist: requests
Requires-Dist: tensorflow
